{
    "viafID": "110926589",
    "ISNI": [
        "000000012147772X"
    ],
    "Library of Congress\/NACO": [
        "n84156475"
    ],
    "National Library of the Netherlands": [
        "074236911"
    ],
    "Wikidata": [
        "Q104027"
    ],
    "Identities": [
        "https:\/\/www.worldcat.org\/identities\/lccn-n84156475"
    ],
    "Wikipedia": [
        "https:\/\/de.wikipedia.org\/wiki\/Kirk_Douglas",
        "https:\/\/en.wikipedia.org\/wiki\/Kirk_Douglas",
        "https:\/\/es.wikipedia.org\/wiki\/Kirk_Douglas",
        "https:\/\/fr.wikipedia.org\/wiki\/Kirk_Douglas",
        "https:\/\/it.wikipedia.org\/wiki\/Kirk_Douglas",
        "https:\/\/nl.wikipedia.org\/wiki\/Kirk_Douglas",
        "https:\/\/simple.wikipedia.org\/wiki\/Kirk_Douglas"
    ]
}